darkarp/__init__.py
darkarp/malkit_modules/__init__.py
darkarp/malkit_modules/build.py
darkarp/malkit_modules/cookiesteal.py
darkarp/malkit_modules/encrypt.py
darkarp/malkit_modules/identifiers.py
darkarp-3.5.dist-info/LICENSE.txt
darkarp-3.5.dist-info/METADATA
darkarp-3.5.dist-info/WHEEL
darkarp-3.5.dist-info/top_level.txt
darkarp-3.5.dist-info/RECORD
