Metadata-Version: 2.1
Name: darkarp
Version: 3.5
Summary: Collection of modules by darkArp
Home-page: https://github.com/darkarp
Author: Mario Nascimento
Author-email: marionascimento@itsec.bz
License: MIT
Download-URL: https://github.com/darkarp/darkarp/archive/v3.5.tar.gz
Keywords: darkarp,encryption,malkit
Platform: UNKNOWN
Classifier: Development Status :: 3 - Alpha
Classifier: Intended Audience :: Developers
Classifier: Topic :: Software Development :: Build Tools
Classifier: License :: OSI Approved :: MIT License
Classifier: Programming Language :: Python :: 3.5
Classifier: Programming Language :: Python :: 3.6
Classifier: Programming Language :: Python :: 3.7
Classifier: Programming Language :: Python :: 3.8
